.gitignore
.gitlab-ci.yml
LICENSE
Makefile
README.md
pyproject.toml
setup.py
notebook/transform_GW.ipynb
test/test_wdm.py
wdm_wavelet/__init__.py
wdm_wavelet/_version.py
wdm_wavelet/fourier_coeff.py
wdm_wavelet/wdm.py
wdm_wavelet.egg-info/PKG-INFO
wdm_wavelet.egg-info/SOURCES.txt
wdm_wavelet.egg-info/dependency_links.txt
wdm_wavelet.egg-info/requires.txt
wdm_wavelet.egg-info/top_level.txt
wdm_wavelet/core/__init__.py
wdm_wavelet/core/get_filter.py
wdm_wavelet/core/t2w.py
wdm_wavelet/core/w2t.py
wdm_wavelet/types/__init__.py
wdm_wavelet/types/time_frequency_map.py