Metadata-Version: 2.1
Name: wdm-wavelet
Version: 0.1.1
Summary: A Python package for Wilson-Daubechies-Meyer (WDM) wavelet from coherentWaveBurst
Home-page: https://git.ligo.org/yumeng.xu/setup.py
Author: Yumeng Xu
Author-email: The PycWB team <yumeng.xu@ligo.org>
Keywords: ligo,wavelet,gravitational waves,burst,DWT,WDM,Wilson-Daubechies-Meyer,cWB
Requires-Python: >=3.8
License-File: LICENSE
Requires-Dist: numpy
Requires-Dist: numba
Requires-Dist: rocket-fft
Requires-Dist: gwpy
